mease_elabftw/__init__.py
mease_elabftw/experiments.py
mease_elabftw/linked_items.py
mease_elabftw/logger.py
mease_elabftw/metadata.py
mease_elabftw/nwb.py
mease_elabftw/parsing.py
mease_elabftw/util.py
mease_elabftw/scripts/__init__.py
mease_elabftw/scripts/cli.py
mease_elabftw-0.0.7.dist-info/LICENSE
mease_elabftw-0.0.7.dist-info/METADATA
mease_elabftw-0.0.7.dist-info/WHEEL
mease_elabftw-0.0.7.dist-info/entry_points.txt
mease_elabftw-0.0.7.dist-info/top_level.txt
mease_elabftw-0.0.7.dist-info/RECORD
