Metadata-Version: 2.1
Name: mease-elabftw
Version: 0.0.7
Summary: Extracts metadata from eLabFTW experiments
Home-page: https://github.com/ssciwr/mease-elabftw
Author: Liam Keegan
Author-email: liam@keegan.ch
License: MIT
Project-URL: Documentation, https://mease-elabftw.readthedocs.io/
Project-URL: Issues, https://github.com/ssciwr/mease-elabftw/issues
Classifier: License :: OSI Approved :: MIT License
Classifier: Intended Audience :: Science/Research
Classifier: Intended Audience :: Education
Classifier: Natural Language :: English
Classifier: Operating System :: MacOS :: MacOS X
Classifier: Operating System :: Microsoft :: Windows
Classifier: Operating System :: POSIX :: Linux
Classifier: Programming Language :: Python :: 3 :: Only
Classifier: Programming Language :: Python :: 3.6
Classifier: Programming Language :: Python :: 3.7
Classifier: Programming Language :: Python :: 3.8
Classifier: Programming Language :: Python :: 3.9
Classifier: Programming Language :: Python :: 3.10
License-File: LICENSE
Requires-Dist: click
Requires-Dist: elabapy
Requires-Dist: requests
Requires-Dist: setuptools
Requires-Dist: pynwb
